pygetty/__init__.py
pygetty/assetchanges.py
pygetty/assets.py
pygetty/auth.py
pygetty/collections.py
pygetty/consts.py
pygetty/downloads.py
pygetty/formatters.py
pygetty/images.py
pygetty/network.py
pygetty/search.py
pygetty/usage.py
pygetty/util.py
pygetty/videos.py
pygetty-1.3.5.dist-info/LICENSE
pygetty-1.3.5.dist-info/WHEEL
pygetty-1.3.5.dist-info/METADATA
pygetty-1.3.5.dist-info/RECORD
