Metadata-Version: 2.1
Name: pygetty
Version: 1.3.5
Summary: Wrapper for Getty v3 API
Home-page: https://github.com/Lumen5/pygetty
License: UNKNOWN
Author: Josh Klar
Author-email: josh@lumen5.com
Classifier: License :: OSI Approved :: ISC License (ISCL)
Requires-Dist: requests>=2.20.0
Requires-Dist: future
Requires-Dist: pendulum~=2.0
